{
 "cells": [
  {
   "cell_type": "markdown",
   "id": "84baf0a4",
   "metadata": {},
   "source": [
    "# Where Python Actually Starts\n",
    "A Python file looks calm on the screen, but the moment execution begins the interpreter starts building frames, loading constants, resolving names, and moving through bytecode one instruction at a time. This notebook begins from that living runtime picture so that later topics feel connected instead of scattered."
   ]
  },
  {
   "cell_type": "markdown",
   "id": "59a4fbe7",
   "metadata": {},
   "source": [
    "When people struggle with **Where Python Actually Starts**, the struggle is often not about syntax. It is usually about trying to reason from surface appearance alone. Python rewards a deeper habit: do not ask only what the code *looks like*; ask what objects exist, what names or attributes point to them, what bytecode-level actions are likely happening, and which runtime protocol is being used.\n",
    "\n",
    "That habit is what turns memorized rules into real understanding. It also makes interviews easier, because you stop giving slogan answers and start giving mechanism-based answers.\n"
   ]
  },
  {
   "cell_type": "markdown",
   "id": "fa33dad9",
   "metadata": {},
   "source": [
    "- See the difference between source code, bytecode, and runtime execution\n",
    "- Understand what a frame is in practical terms\n",
    "- Separate names from objects early\n",
    "- Build a mental picture that will support everything else\n"
   ]
  },
  {
   "cell_type": "markdown",
   "id": "e1943c46",
   "metadata": {},
   "source": [
    "At runtime, Python keeps namespaces that map names to objects. A frame carries local names, links to global names, and information about where execution currently is. The important human insight is this: values do not float around alone. They are reached through names, containers, attributes, and call frames.\n"
   ]
  },
  {
   "cell_type": "code",
   "execution_count": 1,
   "id": "5be1dc26",
   "metadata": {
    "execution": {
     "iopub.execute_input": "2026-03-15T13:20:56.338821Z",
     "iopub.status.busy": "2026-03-15T13:20:56.338821Z",
     "iopub.status.idle": "2026-03-15T13:20:56.349365Z",
     "shell.execute_reply": "2026-03-15T13:20:56.349365Z"
    }
   },
   "outputs": [
    {
     "name": "stdout",
     "output_type": "stream",
     "text": [
      "id(x): 140715746449480\n",
      "id(text): 2688898746352\n",
      "id(values): 2688950250688\n",
      "[42, 'python']\n"
     ]
    }
   ],
   "source": [
    "x = 42\n",
    "text = \"python\"\n",
    "values = [x, text]\n",
    "print(\"id(x):\", id(x))\n",
    "print(\"id(text):\", id(text))\n",
    "print(\"id(values):\", id(values))\n",
    "print(values)\n"
   ]
  },
  {
   "cell_type": "markdown",
   "id": "a0a300ff",
   "metadata": {},
   "source": [
    "Bytecode is not something you must memorize, but it is the best way to see that Python lowers your code into smaller runtime instructions. Seeing it once makes the interpreter feel less mystical and more concrete.\n"
   ]
  },
  {
   "cell_type": "code",
   "execution_count": 2,
   "id": "24572d46",
   "metadata": {
    "execution": {
     "iopub.execute_input": "2026-03-15T13:20:56.349365Z",
     "iopub.status.busy": "2026-03-15T13:20:56.349365Z",
     "iopub.status.idle": "2026-03-15T13:20:56.354910Z",
     "shell.execute_reply": "2026-03-15T13:20:56.354910Z"
    }
   },
   "outputs": [
    {
     "name": "stdout",
     "output_type": "stream",
     "text": [
      "  3           0 RESUME                   0\n",
      "\n",
      "  4           2 LOAD_CONST               1 (0)\n",
      "              4 STORE_FAST               1 (s)\n",
      "\n",
      "  5           6 LOAD_GLOBAL              1 (NULL + range)\n",
      "             18 LOAD_FAST                0 (n)\n",
      "             20 PRECALL                  1\n",
      "             24 CALL                     1\n",
      "             34 GET_ITER\n",
      "        >>   36 FOR_ITER                 7 (to 52)\n",
      "             38 STORE_FAST               2 (i)\n",
      "\n",
      "  6          40 LOAD_FAST                1 (s)\n",
      "             42 LOAD_FAST                2 (i)\n",
      "             44 BINARY_OP               13 (+=)\n",
      "             48 STORE_FAST               1 (s)\n",
      "             50 JUMP_BACKWARD            8 (to 36)\n",
      "\n",
      "  7     >>   52 LOAD_FAST                1 (s)\n",
      "             54 RETURN_VALUE\n"
     ]
    }
   ],
   "source": [
    "import dis\n",
    "\n",
    "def total(n):\n",
    "    s = 0\n",
    "    for i in range(n):\n",
    "        s += i\n",
    "    return s\n",
    "\n",
    "dis.dis(total)\n"
   ]
  },
  {
   "cell_type": "markdown",
   "id": "04b79611",
   "metadata": {},
   "source": [
    "The file or notebook cell you write is only the human-friendly layer. Python still has to parse it and turn it into executable instructions.\n",
    "\n",
    "Whenever you call a function, Python creates a new execution frame. That frame holds local variables and remembers where control should return afterward.\n",
    "\n",
    "The name `x` is not the integer itself. It is a reference in some namespace that points to an object.\n",
    "\n",
    "Many “advanced” Python facts stop feeling advanced once you keep the frame and object model in your head.\n"
   ]
  },
  {
   "cell_type": "markdown",
   "id": "60aac6fd",
   "metadata": {},
   "source": [
    "Each call to `describe` gets its own local variables, even though the function body is the same.\n"
   ]
  },
  {
   "cell_type": "code",
   "execution_count": 3,
   "id": "24db42f5",
   "metadata": {
    "execution": {
     "iopub.execute_input": "2026-03-15T13:20:56.354910Z",
     "iopub.status.busy": "2026-03-15T13:20:56.354910Z",
     "iopub.status.idle": "2026-03-15T13:20:56.360455Z",
     "shell.execute_reply": "2026-03-15T13:20:56.360455Z"
    }
   },
   "outputs": [
    {
     "name": "stdout",
     "output_type": "stream",
     "text": [
      "inside with 10\n",
      "inside with 'python'\n"
     ]
    }
   ],
   "source": [
    "def describe(value):\n",
    "    local_message = f\"inside with {value!r}\"\n",
    "    print(local_message)\n",
    "\n",
    "describe(10)\n",
    "describe(\"python\")\n"
   ]
  },
  {
   "cell_type": "markdown",
   "id": "7d614d2f",
   "metadata": {},
   "source": [
    "This exception is intentional. The traceback is showing the chain of frames that led to the problem.\n"
   ]
  },
  {
   "cell_type": "code",
   "execution_count": 4,
   "id": "cca3b82d",
   "metadata": {
    "execution": {
     "iopub.execute_input": "2026-03-15T13:20:56.360455Z",
     "iopub.status.busy": "2026-03-15T13:20:56.360455Z",
     "iopub.status.idle": "2026-03-15T13:20:56.366199Z",
     "shell.execute_reply": "2026-03-15T13:20:56.366199Z"
    }
   },
   "outputs": [
    {
     "name": "stderr",
     "output_type": "stream",
     "text": [
      "Traceback (most recent call last):\n",
      "  File \"C:\\Users\\VIHAAN\\AppData\\Local\\Temp\\ipykernel_15832\\2221454973.py\", line 11, in <module>\n",
      "    a()\n",
      "  File \"C:\\Users\\VIHAAN\\AppData\\Local\\Temp\\ipykernel_15832\\2221454973.py\", line 2, in a\n",
      "    b()\n",
      "  File \"C:\\Users\\VIHAAN\\AppData\\Local\\Temp\\ipykernel_15832\\2221454973.py\", line 5, in b\n",
      "    c()\n",
      "  File \"C:\\Users\\VIHAAN\\AppData\\Local\\Temp\\ipykernel_15832\\2221454973.py\", line 8, in c\n",
      "    raise ValueError(\"trace me\")\n",
      "ValueError: trace me\n"
     ]
    }
   ],
   "source": [
    "def a():\n",
    "    b()\n",
    "\n",
    "def b():\n",
    "    c()\n",
    "\n",
    "def c():\n",
    "    raise ValueError(\"trace me\")\n",
    "\n",
    "try:\n",
    "    a()\n",
    "except ValueError as exc:\n",
    "    import traceback\n",
    "    traceback.print_exc()\n"
   ]
  },
  {
   "cell_type": "markdown",
   "id": "f2ac8cb8",
   "metadata": {},
   "source": [
    "A function carries a code object that stores compiled information about the function body.\n"
   ]
  },
  {
   "cell_type": "code",
   "execution_count": 5,
   "id": "b158de27",
   "metadata": {
    "execution": {
     "iopub.execute_input": "2026-03-15T13:20:56.366199Z",
     "iopub.status.busy": "2026-03-15T13:20:56.366199Z",
     "iopub.status.idle": "2026-03-15T13:20:56.371398Z",
     "shell.execute_reply": "2026-03-15T13:20:56.371398Z"
    }
   },
   "outputs": [
    {
     "name": "stdout",
     "output_type": "stream",
     "text": [
      "<code object sample at 0x0000027211EDC5E0, file \"C:\\Users\\VIHAAN\\AppData\\Local\\Temp\\ipykernel_15832\\2060303189.py\", line 1>\n",
      "('a', 'b')\n"
     ]
    }
   ],
   "source": [
    "def sample(a, b):\n",
    "    return a + b\n",
    "\n",
    "print(sample.__code__)\n",
    "print(sample.__code__.co_varnames)\n"
   ]
  },
  {
   "cell_type": "markdown",
   "id": "3635db3f",
   "metadata": {},
   "source": [
    "This is not only a classroom topic. **Where Python Actually Starts** usually appears in real projects as a debugging problem, a design choice, a performance tradeoff, or a readability decision. In other words, this topic matters most when the codebase gets large enough that vague intuition stops being reliable.\n",
    "\n",
    "That is why the low-level view is useful. It gives you something firmer than guesswork when code starts behaving in surprising ways.\n"
   ]
  },
  {
   "cell_type": "markdown",
   "id": "36a469ed",
   "metadata": {},
   "source": [
    "- Thinking a variable is the same thing as the object it names\n",
    "- Treating bytecode as irrelevant trivia instead of a useful mental tool\n",
    "- Ignoring frames when reading tracebacks\n"
   ]
  },
  {
   "cell_type": "markdown",
   "id": "c344b38f",
   "metadata": {},
   "source": [
    "- What happens between Python source code and execution?\n",
    "- What is a frame?\n",
    "- What is the difference between a name and an object?\n"
   ]
  },
  {
   "cell_type": "markdown",
   "id": "6582dbec",
   "metadata": {},
   "source": [
    "- Python executes compiled instructions, not raw text.\n",
    "- Frames are the working spaces of execution.\n",
    "- Names point to objects through namespaces.\n"
   ]
  },
  {
   "cell_type": "markdown",
   "id": "34cac00b",
   "metadata": {},
   "source": [
    "If this notebook did its job, **Where Python Actually Starts** should now feel less like a bag of special rules and more like a natural consequence of Python's runtime model. That is the standard we want: not just recall, but a calm explanation of what the interpreter is seeing and why the behavior follows from that.\n"
   ]
  },
  {
   "cell_type": "markdown",
   "id": "5a669ab0",
   "metadata": {},
   "source": [
    "A better way to understand Where Python Actually Starts is to keep moving back and forth between three views of the same code.\n",
    "\n",
    "The first view is the human view. This is what the code is trying to say. The second view is the object view. In that view, we ask which Python objects exist, which names refer to them, and which objects are being created, reused, mutated, or discarded. The third view is the interpreter view. In that view, we ask what protocol is being used, what bytecode is being executed, and which runtime rules are controlling the result.\n",
    "\n",
    "Many learners stop after the first view. That is enough to copy code, but it is usually not enough to explain surprising behavior. Deep understanding starts when these three views become one mental movement instead of three unrelated topics.\n"
   ]
  },
  {
   "cell_type": "markdown",
   "id": "04fc7c44",
   "metadata": {},
   "source": [
    "There is also a fourth habit that helps a lot: failure-based thinking.\n",
    "\n",
    "For Where Python Actually Starts, ask yourself what normally goes wrong when the idea is only half-understood. Does someone confuse identity with equality? Do they expect copying where only rebinding happened? Do they expect a fresh iterator when they really have an exhausted one? Do they trust a default value that is secretly shared? Do they think a class attribute is per-instance state? Once you can predict the common failure modes before they happen, your understanding becomes much more stable.\n"
   ]
  },
  {
   "cell_type": "code",
   "execution_count": 6,
   "id": "ea3c073c",
   "metadata": {
    "execution": {
     "iopub.execute_input": "2026-03-15T13:20:56.371398Z",
     "iopub.status.busy": "2026-03-15T13:20:56.371398Z",
     "iopub.status.idle": "2026-03-15T13:20:56.377567Z",
     "shell.execute_reply": "2026-03-15T13:20:56.377567Z"
    }
   },
   "outputs": [
    {
     "name": "stdout",
     "output_type": "stream",
     "text": [
      "locals now: {'value': 'demo', 'local_copy': 'demo', 'frame': <frame at 0x0000027211CF7E80, file 'C:\\\\Users\\\\VIHAAN\\\\AppData\\\\Local\\\\Temp\\\\ipykernel_15832\\\\939914315.py', line 7, code probe_runtime>}\n",
      "demo\n",
      "\n",
      "bytecode for probe_runtime:\n",
      "  4           0 RESUME                   0\n",
      "\n",
      "  5           2 LOAD_FAST                0 (value)\n",
      "              4 STORE_FAST               1 (local_copy)\n",
      "\n",
      "  6           6 LOAD_GLOBAL              0 (inspect)\n",
      "             18 LOAD_METHOD              1 (currentframe)\n",
      "             40 PRECALL                  0\n",
      "             44 CALL                     0\n",
      "             54 STORE_FAST               2 (frame)\n",
      "\n",
      "  7          56 LOAD_GLOBAL              5 (NULL + print)\n",
      "             68 LOAD_CONST               1 ('locals now:')\n",
      "             70 LOAD_FAST                2 (frame)\n",
      "             72 LOAD_ATTR                3 (f_locals)\n",
      "             82 PRECALL                  2\n",
      "             86 CALL                     2\n",
      "             96 POP_TOP\n",
      "\n",
      "  8          98 LOAD_FAST                1 (local_copy)\n",
      "            100 RETURN_VALUE\n"
     ]
    }
   ],
   "source": [
    "import dis\n",
    "import inspect\n",
    "\n",
    "def probe_runtime(value):\n",
    "    local_copy = value\n",
    "    frame = inspect.currentframe()\n",
    "    print('locals now:', frame.f_locals)\n",
    "    return local_copy\n",
    "\n",
    "print(probe_runtime('demo'))\n",
    "print('\\nbytecode for probe_runtime:')\n",
    "dis.dis(probe_runtime)\n"
   ]
  },
  {
   "cell_type": "markdown",
   "id": "e0398f9a",
   "metadata": {},
   "source": [
    "A deeper layer here is to stop thinking about execution as a smooth blur. Execution really advances through concrete steps. Python creates a frame, resolves names, loads constants, calls functions, stores results, and returns values. That is why stack traces, code objects, and disassembly are so valuable. They give you snapshots of those steps instead of leaving everything hidden behind the surface syntax.\n",
    "\n",
    "This is also the right place to begin separating language guarantees from CPython implementation details. The language explains the meaning of the code. CPython explains many of the practical low-level behaviors you observe while running that code.\n"
   ]
  },
  {
   "cell_type": "code",
   "execution_count": 7,
   "id": "1b6b8021",
   "metadata": {
    "execution": {
     "iopub.execute_input": "2026-03-15T13:20:56.377567Z",
     "iopub.status.busy": "2026-03-15T13:20:56.377567Z",
     "iopub.status.idle": "2026-03-15T13:20:56.383692Z",
     "shell.execute_reply": "2026-03-15T13:20:56.383692Z"
    }
   },
   "outputs": [
    {
     "name": "stdout",
     "output_type": "stream",
     "text": [
      "code object name: execution_story\n",
      "line number inside function: 8\n",
      "locals inside frame: {'a': 7, 'b': 8, 'total': 15, 'frame': <frame at 0x0000027211EDE330, file 'C:\\\\Users\\\\VIHAAN\\\\AppData\\\\Local\\\\Temp\\\\ipykernel_15832\\\\2259766311.py', line 9, code execution_story>}\n",
      "15\n",
      "\n",
      "bytecode:\n",
      "  4           0 RESUME                   0\n",
      "\n",
      "  5           2 LOAD_FAST                0 (a)\n",
      "              4 LOAD_FAST                1 (b)\n",
      "              6 BINARY_OP                0 (+)\n",
      "             10 STORE_FAST               2 (total)\n",
      "\n",
      "  6          12 LOAD_GLOBAL              0 (inspect)\n",
      "             24 LOAD_METHOD              1 (currentframe)\n",
      "             46 PRECALL                  0\n",
      "             50 CALL                     0\n",
      "             60 STORE_FAST               3 (frame)\n",
      "\n",
      "  7          62 LOAD_GLOBAL              5 (NULL + print)\n",
      "             74 LOAD_CONST               1 ('code object name:')\n",
      "             76 LOAD_FAST                3 (frame)\n",
      "             78 LOAD_ATTR                3 (f_code)\n",
      "             88 LOAD_ATTR                4 (co_name)\n",
      "             98 PRECALL                  2\n",
      "            102 CALL                     2\n",
      "            112 POP_TOP\n",
      "\n",
      "  8         114 LOAD_GLOBAL              5 (NULL + print)\n",
      "            126 LOAD_CONST               2 ('line number inside function:')\n",
      "            128 LOAD_FAST                3 (frame)\n",
      "            130 LOAD_ATTR                5 (f_lineno)\n",
      "            140 PRECALL                  2\n",
      "            144 CALL                     2\n",
      "            154 POP_TOP\n",
      "\n",
      "  9         156 LOAD_GLOBAL              5 (NULL + print)\n",
      "            168 LOAD_CONST               3 ('locals inside frame:')\n",
      "            170 LOAD_FAST                3 (frame)\n",
      "            172 LOAD_ATTR                6 (f_locals)\n",
      "            182 PRECALL                  2\n",
      "            186 CALL                     2\n",
      "            196 POP_TOP\n",
      "\n",
      " 10         198 LOAD_FAST                2 (total)\n",
      "            200 RETURN_VALUE\n"
     ]
    }
   ],
   "source": [
    "import inspect\n",
    "import dis\n",
    "\n",
    "def execution_story(a, b):\n",
    "    total = a + b\n",
    "    frame = inspect.currentframe()\n",
    "    print('code object name:', frame.f_code.co_name)\n",
    "    print('line number inside function:', frame.f_lineno)\n",
    "    print('locals inside frame:', frame.f_locals)\n",
    "    return total\n",
    "\n",
    "print(execution_story(7, 8))\n",
    "print('\\nbytecode:')\n",
    "dis.dis(execution_story)\n"
   ]
  },
  {
   "cell_type": "markdown",
   "id": "f2252640",
   "metadata": {},
   "source": [
    "One useful way to deepen this chapter is to stop treating execution as a single mysterious event and instead see it as a chain of smaller, understandable events. Python reads source, compiles it, stores constants, creates code objects, enters frames, resolves names, and returns values. None of those pieces are random. They are simply easy to ignore until a bug, a traceback, or a performance question forces you to care. Once you have that layered picture, you can read later notebooks with much more confidence because you are no longer depending on surface syntax alone.\n"
   ]
  },
  {
   "cell_type": "markdown",
   "id": "7d574523",
   "metadata": {},
   "source": [
    "## Final Takeaway\n",
    "\n",
    "The deepest way to revise **Where Python Actually Starts** is to stop treating it as a collection of syntax facts and instead treat it as a runtime story. Ask what objects are involved, what names or attributes point to those objects, what frame is active, and what protocol or bytecode path Python is following. If you can explain this topic at those four levels, then you understand much more than the visible syntax.\n",
    "\n",
    "In interview terms, the strongest answer is usually not the shortest definition. It is a calm explanation of what Python is doing under the surface and why the behavior follows from that model. For revision, come back to this notebook and ask yourself: could I explain this entire chapter with one small code example, one memory-level explanation, and one interpreter-level explanation? If yes, the topic is becoming yours.\n"
   ]
  }
 ],
 "metadata": {
  "kernelspec": {
   "display_name": "Python 3",
   "language": "python",
   "name": "python3"
  },
  "language_info": {
   "codemirror_mode": {
    "name": "ipython",
    "version": 3
   },
   "file_extension": ".py",
   "mimetype": "text/x-python",
   "name": "python",
   "nbconvert_exporter": "python",
   "pygments_lexer": "ipython3",
   "version": "3.11.0"
  }
 },
 "nbformat": 4,
 "nbformat_minor": 5
}
